odoo/addons/payment_redsys/README.rst
odoo/addons/payment_redsys/__init__.py
odoo/addons/payment_redsys/__manifest__.py
odoo/addons/payment_redsys/controllers/__init__.py
odoo/addons/payment_redsys/controllers/main.py
odoo/addons/payment_redsys/data/payment_redsys.xml
odoo/addons/payment_redsys/i18n/bg.po
odoo/addons/payment_redsys/i18n/ca.po
odoo/addons/payment_redsys/i18n/es.po
odoo/addons/payment_redsys/i18n/fr.po
odoo/addons/payment_redsys/i18n/gl.po
odoo/addons/payment_redsys/i18n/hr.po
odoo/addons/payment_redsys/i18n/payment_redsys.pot
odoo/addons/payment_redsys/i18n/pt_BR.po
odoo/addons/payment_redsys/i18n/sl.po
odoo/addons/payment_redsys/models/__init__.py
odoo/addons/payment_redsys/models/redsys.py
odoo/addons/payment_redsys/readme/CONFIGURE.rst
odoo/addons/payment_redsys/readme/CONTRIBUTORS.rst
odoo/addons/payment_redsys/readme/DESCRIPTION.rst
odoo/addons/payment_redsys/readme/INSTALL.rst
odoo/addons/payment_redsys/readme/ROADMAP.rst
odoo/addons/payment_redsys/static/description/icon.png
odoo/addons/payment_redsys/static/description/index.html
odoo/addons/payment_redsys/static/img/bizum.png
odoo/addons/payment_redsys/static/src/img/redsys_icon.png
odoo/addons/payment_redsys/tests/__init__.py
odoo/addons/payment_redsys/tests/test_redsys.py
odoo/addons/payment_redsys/views/payment_acquirer.xml
odoo/addons/payment_redsys/views/payment_redsys_templates.xml
odoo/addons/payment_redsys/views/redsys.xml
odoo13_addon_payment_redsys-13.0.2.0.3.dist-info/METADATA
odoo13_addon_payment_redsys-13.0.2.0.3.dist-info/WHEEL
odoo13_addon_payment_redsys-13.0.2.0.3.dist-info/top_level.txt
odoo13_addon_payment_redsys-13.0.2.0.3.dist-info/RECORD
